slackclient_log_handler/__init__.py
slackclient_log_handler-0.1.2.dist-info/LICENSE
slackclient_log_handler-0.1.2.dist-info/METADATA
slackclient_log_handler-0.1.2.dist-info/WHEEL
slackclient_log_handler-0.1.2.dist-info/RECORD
