Metadata-Version: 2.1
Name: slackclient-log-handler
Version: 0.1.2
Summary: Posts log events to Slack via API
Home-page: https://github.com/search5/slackclient_log_handler
License: Apache-2.0
Keywords: slack,logging
Author: Ji-Ho Lee
Author-email: search5@gmail.com
Requires-Python: >=3.9,<4.0
Classifier: Development Status :: 5 - Production/Stable
Classifier: Environment :: Web Environment
Classifier: Framework :: Django
Classifier: Intended Audience :: Developers
Classifier: Intended Audience :: System Administrators
Classifier: License :: OSI Approved :: Apache Software License
Classifier: Natural Language :: English
Classifier: Operating System :: OS Independent
Classifier: Programming Language :: Python
Classifier: Programming Language :: Python :: 3
Classifier: Programming Language :: Python :: 3.9
Classifier: Programming Language :: Python :: 3.10
Classifier: Programming Language :: Python :: 3.11
Classifier: Programming Language :: Python :: 3
Classifier: Topic :: Communications :: Chat
Classifier: Topic :: Office/Business :: Groupware
Requires-Dist: six (>=1.16.0,<2.0.0)
Requires-Dist: slack-sdk (>=3.26.1,<4.0.0)
Project-URL: Repository, https://github.com/search5/slackclient_log_handler
